
  { "fullText" : "Asʿad, Gabriel https:\/\/gedsh.bethmardutho.org\/Asad-Gabriel http:\/\/syriaca.org\/bibl\/60 51 Gabriel Asʿad http:\/\/syriaca.org\/person\/346 person Teacher and musician, active in the Near East and Sweden. (1907–1997) [ Syr. Orth. ] He was born in Midyat and in 1914 joined Taw Mim Simkath where he studied under Dolabani , under Paul John (an educator from Kharput), and under Ibrahim Haqwirdi. In 1925 he immigrated to Beirut where he learned music and began putting to music the poems and anthems of the writers of this period. He taught in ʿĀmūda, Damascus , Bethlehem, Jerusalem , and Qamishli. In 1953 he published Men musiqi dilan ḥdato in musical notes, and in the 1970s produced two records. He immigrated to Sweden and died in Stockholm. Sources Abūna, Adab , 575. Macuch, Geschichte , 469. Munūfar Barṣūm, Aḍwāʾ , 112–4. George A. Kiraz",
    "title" : "Asʿad, Gabriel",
    "idno" : "https:\/\/gedsh.bethmardutho.org\/Asad-Gabriel",
    "displayTitleEnglish" : "Asʿad, Gabriel",
    "persName" : 
    [ " Dolabani ",
      "  George A.  Kiraz  " ],
    "placeName" : 
    [ " Midyat ",
      " Beirut ",
      " Damascus ",
      " Jerusalem " ] }