
  { "fullText" : "Behnam Ḥadloyo https:\/\/gedsh.bethmardutho.org\/Behnam-Hadloyo http:\/\/syriaca.org\/bibl\/101 92 http:\/\/syriaca.org\/person\/263 person Patr. and liturgical composer. (d. 1454) [ Syr. Orth. ] Patr. and liturgical composer. He was born in Ḥadl of Yūḥannā of the Habbo Kanni family of Barṭelle . He became a monk at the Monastery of Mor Gabriel , was consecrated a Maph. and named Baselius in 1404, and then a Patr. patr. for the see of Mardin on June 1412. After the death of the Ṭur ʿAbdin anti- patr. Baselius V, he managed to unite all the dioceses under his authority in 1445. He composed ten ḥusoye , an Anaphora, and 11 poems. He also compiled selections from the commentary of Daniel of Salaḥ and arranged them with the texts of the Psalms in an autograph ms. dated 1425 ( ms. Jerusalem, St. Mark 14). Sources Barsoum, Scattered pearls , 497–9. Baumstark, Literatur , 327. George A. Kiraz",
    "title" : "Behnam Ḥadloyo",
    "idno" : "https:\/\/gedsh.bethmardutho.org\/Behnam-Hadloyo",
    "displayTitleEnglish" : "Behnam Ḥadloyo",
    "persName" : 
    [ " Daniel of Salaḥ ",
      "  George A.  Kiraz  " ],
    "placeName" : 
    [ " Barṭelle ",
      " Monastery of Mor Gabriel ",
      " Mardin ",
      " Ṭur ʿAbdin " ] }