
  { "fullText" : "Dabbūs, Antoine https:\/\/gedsh.bethmardutho.org\/Dabbus-Antoine http:\/\/syriaca.org\/bibl\/154 145 Antoine Dabbūs http:\/\/syriaca.org\/person\/432 person Teacher and author. (1916–1983) [ Syr. Orth. ] He was born in Fayrūza near Ḥimṣ , and studied at Taw Mim Simkath , graduating in 1934. He studied Syriac under Isḥāq Armalah and Qarabashī . He was the principal of the ʿĀmūda school, taught in Raʾs al-ʿAyn, and co-founded a school in his village. He wrote for a number of periodicals including Ḥdonoyutho Suryoyto (Buenos Aires, ed. Farīd Nuzhā) and Leshono d-Umtho (Beirut, ed. Ibrahim Haqwerdi). His compositions include a number of poems. He translated from Arabic Muʾayyid al-Dīn al-Ṭaghraʾī’s Lāmiyyat al-ʿajam (published in Munūfar Barṣūm), a short poem by Rabindranath Tagore (1861–1941) titled ‘Clouds and Waves’, and Pierre Corneille’s French poem Le Cid . Sources Abūna, Adab , 574. Macuch, Geschichte , 456. Munūfar Barṣūm, Aḍwāʾ , 93–8. George A. Kiraz",
    "title" : "Dabbūs, Antoine",
    "idno" : "https:\/\/gedsh.bethmardutho.org\/Dabbus-Antoine",
    "displayTitleEnglish" : "Dabbūs, Antoine",
    "persName" : 
    [ " Isḥāq Armalah ",
      " Qarabashī ",
      "  George A.  Kiraz  " ],
    "placeName" : 
    [ " Ḥimṣ " ] }