
  { "fullText" : "Danhash, George https:\/\/gedsh.bethmardutho.org\/Danhash-George http:\/\/syriaca.org\/bibl\/159 150 George Danhash http:\/\/syriaca.org\/person\/437 person Educator and minor writer. (1921–1969) [ Syr. Orth. ] Educator and minor writer. Born in Ṣadad, his father died when he was young and he was sent to the Taw Mim Semkath Orphanage in Beirut . He studied Syriac under Isḥāq Armalah and ʿAbd al-Masīḥ Qarabashī . He taught in the Syr. Orth. schools of ʿAmūdā, Qamishli, and Aleppo . He composed a number of nationalistic poems, in particular Motho rḥimto nišo dil(y) ‘O Beloved Nation, you are my symbol’, which is quite popular today. Most of his writings, however, remain unpublished. His poem motho rḥimto was published with musical notation by Gabriel Asʿad (Aleppo, 1935). Sources Munūfar Barṣūm, Aḍwāʾ , 35–8, 63–4. George A. Kiraz",
    "title" : "Danhash, George",
    "idno" : "https:\/\/gedsh.bethmardutho.org\/Danhash-George",
    "displayTitleEnglish" : "Danhash, George",
    "persName" : 
    [ " Isḥāq Armalah ",
      " ʿAbd al-Masīḥ Qarabashī ",
      " Gabriel Asʿad ",
      "  George A.  Kiraz  " ],
    "placeName" : 
    [ " Beirut ",
      " Aleppo " ] }