
  { "fullText" : "Jacob, Cyril https:\/\/gedsh.bethmardutho.org\/Jacob-Cyril http:\/\/syriaca.org\/bibl\/307 298 Cyril Jacob Qurilos Yaʿqub http:\/\/syriaca.org\/person\/569 person Bishop and author. Qurilos Yaʿqub (1912–199?) [ Syr. Orth. ] He was born in ʿAynward in Ṭur ʿAbdin , and joined Dayr al-Zaʿfarān in 1928. In 1930 he was sent to Dayro d-Mor Yaʿqub in Ṣalaḥ were he was tonsured monk by Yūḥannā Kandūr, and then ordained a priest by Dionysios ʿAbdulnūr of Amid . He then served in Midyat , Karburan, Dirbasiyyeh in Syria, Zaḥle in Lebanon, Jerusalem , and Ḥama. In 1959 he was consecrated bp. by Ignatius Yaʿqub III , and in 1971 became the principal of St. Ephrem Seminary in ʿAṭshaneh. In 1975 he assisted bp. Bp. Ivanios Afram in managing the diocese of Ṭur ʿAbdin. He emigrated to Europe and lived in Sweden for sometime some time , then in the Netherlands at St. Ephrem Monastery in the 1980s, then in Sweden again where he died. He co-authored with his brother Asmar Khoury a Ṭuroyo-Syriac lexicon entitled Mhadyono (Sweden, 1985), and composed many poems (some published in Bahro Suryoyo ). A collection of his writings was ed. by Benjamin Atash (Glane, 1990). Sources Macuch, Geschichte , 471. Munūfar Barṣūm, Aḍwāʾ , 125–126. George A. Kiraz",
    "title" : "Jacob, Cyril",
    "idno" : "https:\/\/gedsh.bethmardutho.org\/Jacob-Cyril",
    "displayTitleEnglish" : "Jacob, Cyril",
    "persName" : 
    [ " Ignatius Yaʿqub III ",
      " Asmar Khoury ",
      "  George A.  Kiraz  " ],
    "placeName" : 
    [ " Ṭur ʿAbdin ",
      " Dayr al-Zaʿfarān ",
      " Amid ",
      " Midyat ",
      " Jerusalem " ] }