
  { "fullText" : "Maqdisī, Jeremiah https:\/\/gedsh.bethmardutho.org\/Maqdisi-Jeremiah http:\/\/syriaca.org\/bibl\/355 346 Jeremiah Maqdisī http:\/\/syriaca.org\/person\/612 person Bishop and author. (1847–1929) [Chald.] He was born in Alqosh and attended the Monastery of Rabban Hormizd in 1864. He studied at the Propaganda school from 1869 until 1879. In 1879 he was ordained a priest. In 1888 he became a patriarchal vicar for Siirt , and in 1889 was consecrated a bp. for Zakho. In 1914 he started building a Cathedral there which was completed in 1919. He wrote a grammar titled Grammaire chaldéenne (Mosul, 1889), reprinted by the Iraqi Academy in 1978, and again in 1997 in Serṭo script by Barsaumo Samoil Dogan with the English title Turoṣ Mamlo by Father Jeremia Pilgrim . He translated from Latin into Syriac a book on logic ( ms. ), and another on literary theology (partly published according to Abūna). Sources Abūna, Adab , 504–5. Macuch, Geschichte , 408–9. George A. Kiraz",
    "title" : "Maqdisī, Jeremiah",
    "idno" : "https:\/\/gedsh.bethmardutho.org\/Maqdisi-Jeremiah",
    "displayTitleEnglish" : "Maqdisī, Jeremiah",
    "persName" : 
    [ "  George A.  Kiraz  " ],
    "placeName" : 
    [ " Alqosh ",
      " Monastery of Rabban Hormizd ",
      " Siirt " ] }