
  { "fullText" : "Nuḥ the Lebanese https:\/\/gedsh.bethmardutho.org\/Nuh-the-Lebanese http:\/\/syriaca.org\/bibl\/413 404 http:\/\/syriaca.org\/person\/277 person Author, maph. (1489\/90–1493), and Patr. patr. (1493–1509). (1451–1509) [ Syr. Orth. ] Author, maph. (1489\/90–1493), and Patr. patr. (1493–1509). Born into a Maronite family, he became Syr. Orth. and studied at Dayr Mār Mūsā al-Ḥabashī near Ḥimṣ . According to the continuator of Bar ʿEbroyo ’s Ecclesiastical History he had an excellent knowledge of both Syriac and Arabic. He was ordained bp. of Ḥimṣ with the name Qurillos. He is the author of a number of memre in the dodecasyllabic meter on several subjects (ascetical, theological, and philosophical; injustice committed by Huns and Kurds; an elegy on his teacher Tumo) (published by Yuḥanon Dolabani [Mardin, 1956]). As Patr. patr. he had to intervene in the conflict which opposed Masʿūd of Ṭur ʿAbdin and some senior bishops of the region. Sources Abbeloos and Lamy, Gregorii Barhebraei chronicon ecclesiasticum , vol. 3, 549–63. Macuch, Geschichte , 17. Barsoum, Scattered pearls , 508–9. Herman G. B. Teule",
    "title" : "Nuḥ the Lebanese",
    "idno" : "https:\/\/gedsh.bethmardutho.org\/Nuh-the-Lebanese",
    "displayTitleEnglish" : "Nuḥ the Lebanese",
    "persName" : 
    [ " Bar ʿEbroyo ",
      " Yuḥanon Dolabani ",
      " Masʿūd of Ṭur ʿAbdin ",
      "  Herman G. B.  Teule  " ],
    "placeName" : 
    [ " Dayr Mār Mūsā al-Ḥabashī ",
      " Ḥimṣ " ] }