
  { "fullText" : "Raḥmani, Ignatius Ephrem II https:\/\/gedsh.bethmardutho.org\/Rahmani-Ignatius-Ephrem-II http:\/\/syriaca.org\/bibl\/462 453 Ignatius Ephrem II Raḥmani http:\/\/syriaca.org\/person\/701 person Patr. (1898-1929), scholar, and liturgist. (1848–1929) [ Syr. Cath. ] Patr. (1898–1929), scholar, and liturgist. He was born in Mosul on 7 Nov. 1848 and named Louis. He studied at the Dominican School under Clemens Joseph David and in 1863 was sent to study in Rome, where he was ordained in 1873. On his return to Mosul he helped in editorial tasks at the Dominican Press. In 1880 he became a Chorepiscopos, and in 1887 was consecrated by Ignatius Giwargis V as titular bp. of Edessa , with the name Rabbula Ephrem. He organized the seventh Synod of Sharfeh , and in 1890 became bp. of Baghdad , and then of Aleppo in 1894. Following his election as Patr. patr. in 1898 he renovated the Sharfeh press, moved the patriarchate from Mardin to Beirut , founded the seminary school in Jerusalem (1902), and restored Dayro d-Mor Behnam . His most important publications of Syriac were the Testament of our Lord Jesus Christ (1899, with LT ), Martyrdom of Shmona and Gurya (1899, with LT ), the Chronicle of 1234 (1904), Studia Syriaca , I–V (1904–9; the last volume containing Anṭun of Tagrit ’s book on poetics), and Ktobo d-ṭekso d-qurobo  \/ Missale (1922). His Les liturgies orientales et occidentales (1934, in Arabic) was a pioneering study of comparative liturgy. See Fig. 106 . Sources Abuna, Adab , 603–7. Macuch, Geschichte , 429–32. D.  Aphram Naqqashe, ʿInāyat al-raḥmān fī hidāyat al-suryān (1910), 668. Ph. de Tarrazi, al-Salāsil al-tārikhiyya (1910), 392–400. Ph. de Tarrazi idem , Aṣdaq mā kān ʿan taʾrīkh Lubnān (1948), vol. 1, 408–18. Sebastian P. Brock and George A. Kiraz",
    "title" : "Raḥmani, Ignatius Ephrem II",
    "idno" : "https:\/\/gedsh.bethmardutho.org\/Rahmani-Ignatius-Ephrem-II",
    "displayTitleEnglish" : "Raḥmani, Ignatius Ephrem II",
    "persName" : 
    [ " Clemens Joseph David ",
      " Anṭun of Tagrit ",
      "  Sebastian P.  Brock  ",
      "  George A.  Kiraz  " ],
    "placeName" : 
    [ " Mosul ",
      " Edessa ",
      " Sharfeh ",
      " Baghdad ",
      " Aleppo ",
      " Mardin ",
      " Beirut ",
      " Jerusalem ",
      " Dayro d-Mor Behnam " ] }