
  { "fullText" : "Sawma, Abrohom https:\/\/gedsh.bethmardutho.org\/Sawma-Abrohom http:\/\/syriaca.org\/bibl\/483 474 Abrohom Sawma http:\/\/syriaca.org\/person\/720 person Author. (1913–1996) [ Syr. Orth. ] He was born in Midyat and joined Taw Mim Simkath in 1919 in Adana where he learned Syriac under Dolabani . He moved with the school to Beirut in 1923 and studied there under Armalah . He lived in Jerusalem in 1928 where he studied at St. Mark’s Monastery , then joined public schools and graduated as an engineer in 1943. In 1948 he left Jerusalem and lived in Brazil. His Syriac writings include poems, some published in Ḥdoyutho Suryoyto (Buenos Aires, ed. Farīd Nozha), and an 11-volume set titled Ktobo d-marduto d-suryoye (1967–1990). He also wrote Mtumoyuto d-suryoye (São Paulo, 1996) and a play on Abgar V Ukkama in Arabic. Sources Abūna, Adab , 576. Macuch, Geschichte , 470. Munūfar Barṣūm, Aḍwāʾ , 129–31. George A. Kiraz",
    "title" : "Sawma, Abrohom",
    "idno" : "https:\/\/gedsh.bethmardutho.org\/Sawma-Abrohom",
    "displayTitleEnglish" : "Sawma, Abrohom",
    "persName" : 
    [ " Dolabani ",
      " Armalah ",
      "  George A.  Kiraz  " ],
    "placeName" : 
    [ " Midyat ",
      " Beirut ",
      " Jerusalem ",
      " St. Mark’s Monastery " ] }